pulumi_aws_apigateway/__init__.py
pulumi_aws_apigateway/_enums.py
pulumi_aws_apigateway/_inputs.py
pulumi_aws_apigateway/_utilities.py
pulumi_aws_apigateway/provider.py
pulumi_aws_apigateway/pulumi-plugin.json
pulumi_aws_apigateway/py.typed
pulumi_aws_apigateway/rest_api.py
pulumi_aws_apigateway-2.6.2.dist-info/METADATA
pulumi_aws_apigateway-2.6.2.dist-info/WHEEL
pulumi_aws_apigateway-2.6.2.dist-info/top_level.txt
pulumi_aws_apigateway-2.6.2.dist-info/RECORD
