Metadata-Version: 2.2
Name: pulumi_aws_apigateway
Version: 2.6.2
Summary: Pulumi Amazon Web Services (AWS) API Gateway Components.
License: Apache-2.0
Project-URL: Repository, https://github.com/pulumi/pulumi-aws-apigateway
Keywords: pulumi,aws,apigateway,category/cloud,kind/component
Requires-Python: >=3.9
Requires-Dist: parver>=0.2.1
Requires-Dist: pulumi<4.0.0,>=3.142.0
Requires-Dist: pulumi-aws<7.0.0,>=6.59.1
Requires-Dist: semver>=2.8.1
Requires-Dist: typing-extensions>=4.11; python_version < "3.11"
